aiomemoize.py
aiomemoize-0.0.3.dist-info/LICENSE
aiomemoize-0.0.3.dist-info/METADATA
aiomemoize-0.0.3.dist-info/WHEEL
aiomemoize-0.0.3.dist-info/top_level.txt
aiomemoize-0.0.3.dist-info/RECORD
