Metadata-Version: 2.1
Name: aiomemoize
Version: 0.0.3
Summary: Memoize asyncio Python function calls
Home-page: https://github.com/michalc/aiomemoize
Author: Michal Charemza
Author-email: michal@charemza.name
License: UNKNOWN
Platform: UNKNOWN
Classifier: Programming Language :: Python :: 3
Classifier: License :: OSI Approved :: MIT License
Classifier: Operating System :: OS Independent
Classifier: Framework :: AsyncIO
Requires-Python: ~=3.5
